gitlab_lint/__init__.py
gitlab_lint/gll.py
gitlab_lint-0.4.0.dist-info/LICENSE.txt
gitlab_lint-0.4.0.dist-info/METADATA
gitlab_lint-0.4.0.dist-info/WHEEL
gitlab_lint-0.4.0.dist-info/entry_points.txt
gitlab_lint-0.4.0.dist-info/top_level.txt
gitlab_lint-0.4.0.dist-info/RECORD
