Metadata-Version: 2.1
Name: gitlab-lint
Version: 0.4.0
Summary: This is a CLI application to quickly lint .gitlab-ci.yml files using the gitlab api
Home-page: UNKNOWN
Author: Elijah Roberts
Author-email: elijah@elijahjamesroberts.com
License: MIT
Download-URL: https://github.com/elijah-roberts/gitlab_lint/archive/0.3.0.tar.gz
Keywords: GITLAB,LINT,GIT
Platform: UNKNOWN
Classifier: Programming Language :: Python :: 3
Classifier: License :: OSI Approved :: MIT License
Classifier: Operating System :: OS Independent
Requires-Python: >=3.6
License-File: LICENSE.txt
Requires-Dist: Click
Requires-Dist: Requests
